{
  "history": [
    {
      "command": "open terminal",
      "time": "2025-07-17 19:02:34.002806"
    },
    {
      "command": "open terminal",
      "time": "2025-07-17 19:02:44.501027"
    },
    {
      "command": "what is time",
      "time": "2025-07-17 19:03:03.483074"
    },
    {
      "command": "what is time",
      "time": "2025-07-17 19:03:06.208040"
    },
    {
      "command": "what is time",
      "time": "2025-07-17 19:03:07.102106"
    },
    {
      "command": "what is timw",
      "time": "2025-07-17 19:05:09.258698"
    },
    {
      "command": "what's time?",
      "time": "2025-07-17 19:05:21.954822"
    },
    {
      "command": "help",
      "time": "2025-07-17 19:09:04.818402"
    },
    {
      "command": "helo",
      "time": "2025-07-17 19:18:55.032610"
    },
    {
      "command": "what's time?",
      "time": "2025-07-17 19:19:09.175811"
    },
    {
      "command": "what time is it",
      "time": "2025-07-17 19:36:03.570457"
    },
    {
      "command": "sean your logs logs",
      "time": "2025-07-17 19:36:35.834654"
    },
    {
      "command": "watch watch diaries or is it did",
      "time": "2025-07-17 19:37:04.343661"
    },
    {
      "command": "what what the time he time is is it it",
      "time": "2025-07-17 19:37:27.342271"
    },
    {
      "command": "open firefox",
      "time": "2025-07-17 19:52:55.315414"
    },
    {
      "command": "hope open fire fire fire for fox",
      "time": "2025-07-17 19:52:56.362773"
    },
    {
      "command": "open firefox",
      "time": "2025-07-17 19:53:13.847654"
    },
    {
      "command": "hope open fire fire fire for fox",
      "time": "2025-07-17 19:53:17.811880"
    },
    {
      "command": "how are you",
      "time": "2025-07-17 20:03:22.334194"
    },
    {
      "command": "hope open fire firefox",
      "time": "2025-07-17 20:03:46.831594"
    },
    {
      "command": "how are you",
      "time": "2025-07-17 20:03:56.696853"
    },
    {
      "command": "open firefox",
      "time": "2025-07-17 20:04:04.944041"
    }
  ]
}